vrage_api/__init__.py
vrage_api/vrage_api.py
vrage_api-1.0.2.dist-info/LICENSE.txt
vrage_api-1.0.2.dist-info/METADATA
vrage_api-1.0.2.dist-info/WHEEL
vrage_api-1.0.2.dist-info/top_level.txt
vrage_api-1.0.2.dist-info/RECORD
