Metadata-Version: 2.1
Name: vrage_api
Version: 1.0.2
Summary: Python Request Wrapper for Space Engineers Dedicated Server Remote API (VRage API)
Home-page: https://github.com/BSpendlove/vrage_api
Author: Brandon Spendlove
Author-email: br@ndonspendlove.dev
License: MIT
Project-URL: Documentation, https://github.com/BSpendlove/vrage_api
Platform: any
Classifier: Development Status :: 4 - Beta
Classifier: Programming Language :: Python
License-File: LICENSE.txt
Requires-Dist: importlib-metadata; python_version < "3.8"
Requires-Dist: requests; python_version < "3.8"
Requires-Dist: loguru; python_version < "3.8"
Requires-Dist: python-dotenv; python_version < "3.8"
Provides-Extra: testing
Requires-Dist: setuptools; extra == "testing"
Requires-Dist: pytest; extra == "testing"
Requires-Dist: pytest-cov; extra == "testing"
